imagetoolbox.py
imagetoolbox-0.0.1.dist-info/LICENSE.txt
imagetoolbox-0.0.1.dist-info/METADATA
imagetoolbox-0.0.1.dist-info/WHEEL
imagetoolbox-0.0.1.dist-info/top_level.txt
imagetoolbox-0.0.1.dist-info/RECORD
