Metadata-Version: 2.1
Name: imagetoolbox
Version: 0.0.1
Summary: This pacakage will provide various functions to easily manipulate image.
Home-page: UNKNOWN
Author: Debangshu Chakraborty
Author-email: debangshuchakraborty25@gmail.com
License: UNKNOWN
Platform: UNKNOWN
Classifier: Programming Language :: Python :: 3
Classifier: License :: OSI Approved :: MIT License
Classifier: Operating System :: OS Independent
